<?xml version="1.0" encoding="utf-8"?>
<odoo>

    <!--
    <record model="ir.ui.view" id="view_sales_team_tree">
        <field name="name">crm.team.tree.addresto.inherit</field>
        <field name="model">crm.team</field>
        <field name="inherit_id" ref="sales_team.crm_team_view_tree"/>
        <field name="arch" type="xml">
            <xpath expr="//tree" position="attributes">
                <attribute name="js_class">wx_tools_team_tree</attribute>
            </xpath>
        </field>
    </record>
    -->

    <record id="crm_team_qrcodeimg" model="ir.ui.view">
        <field name="name">crm.team.form.qrcodeimg</field>
        <field name="model">crm.team</field>
        <field name="inherit_id" ref="sales_team.crm_team_view_form"/>
        <field name="arch" type="xml">
            <xpath expr="//field[@name='alias_contact']" position="after">
                <field name="qrcodeimg"/>
            </xpath>
        </field>
    </record>


    <record id="view_crm_team_wx_address_location" model="ir.ui.view">
        <field name="name">crm.team.form.wx_address_location</field>
        <field name="model">crm.team</field>
        <field name="priority">2</field>
        <field name="inherit_id" ref="sales_team.crm_team_view_form"/>
        <field name="arch" type="xml">
            <xpath expr="//page[@name='dashboard']" position="after">
                <page string="门店坐标">
                    <group name="group_address_location">
                        <field name="longitude"/>
                        <field name="latitude"/>
                        <field name="location_write_date"/>
                        <field name="address_location"/>
                        <script type="text/javascript">
                            getWXLocation() //获取当前微信地址，微信地址已转换为实际地址，可以直接使用。
                            $("[name='address_location']").addClass("o_form_uri o_field_widget");
                            $("[name='street']").addClass("o_form_uri o_field_widget");
                            $("[name='address_location']").bind("click",function(){
                            //打开地图，
                            openLocation($("[name='latitude']").text(),$("[name='longitude']").text(),$("[name='address_location']").text(),$("[name='address_location']").text())
                            });
                            $("[name='street']").bind("click",function(){
                            openLocation($("[name='latitude']").text(),$("[name='longitude']").text(),$("[name='address_location']").text(),$("[name='address_location']").text())
                            });
                        </script>
                    </group>
                </page>
            </xpath>
        </field>
    </record>


</odoo>
